medicalai/__about__.py
medicalai/__init__.py
medicalai/chief/__init__.py
medicalai/chief/core.py
medicalai/chief/dataset_analysis.py
medicalai/chief/dataset_prepare.py
medicalai/chief/download_utils.py
medicalai/chief/networks.py
medicalai/chief/prettyloss.py
medicalai/chief/uFuncs.py
medicalai/chief/callbacks/__init__.py
medicalai/chief/callbacks/custom_callbacks.py
medicalai/chief/dataloaders/__init__.py
medicalai/chief/dataloaders/data_utils.py
medicalai/chief/dataloaders/dataset_processors.py
medicalai/chief/dataloaders/dataset_visualize.py
medicalai/chief/dataloaders/image_sequences.py
medicalai/chief/dataloaders/tf_image_pipelines.py
medicalai/chief/model_metrics/__init__.py
medicalai/chief/model_metrics/modelstats.py
medicalai/chief/nnets/__init__.py
medicalai/chief/nnets/covid_net.py
medicalai/chief/nnets/densenet.py
medicalai/chief/nnets/inceptionResnet.py
medicalai/chief/nnets/inceptionv3.py
medicalai/chief/nnets/mobilenet.py
medicalai/chief/nnets/mobilenetv2.py
medicalai/chief/nnets/resnet.py
medicalai/chief/nnets/vgg16.py
medicalai/chief/nnets/xception.py
medicalai/chief/xai/__init__.py
medicalai/chief/xai/xcams.py
tests/__init__.py
tests/test_dataset_analysis.py
tests/test_dataset_prepare.py
tests/test_networks.py
medicalai-1.3.1.dist-info/LICENSE
medicalai-1.3.1.dist-info/METADATA
medicalai-1.3.1.dist-info/WHEEL
medicalai-1.3.1.dist-info/top_level.txt
medicalai-1.3.1.dist-info/zip-safe
medicalai-1.3.1.dist-info/RECORD
