Metadata-Version: 2.1
Name: medicalai
Version: 1.3.1
Summary: Medical-AI is a AI framework specifically for Medical Applications
Home-page: https://github.com/aibharata/medicalAI
Download-URL: https://github.com/aibharata/medicalAI/archive/v1.2.8-rc.zip
Author: Vinayaka Jyothi - For AiBharata
Author-email: contact@aibharata.com
License: Apache
Keywords: AI Framework,Medical AI,Tensorflow,radiology AI
Classifier: Development Status :: 3 - Alpha
Classifier: Intended Audience :: Science/Research
Classifier: Topic :: Scientific/Engineering :: Artificial Intelligence
Classifier: License :: OSI Approved :: Apache Software License
Classifier: Programming Language :: Python :: 3.5
Classifier: Programming Language :: Python :: 3.6
Classifier: Programming Language :: Python :: 3.7
Requires-Python: >=3.5, <3.9
License-File: LICENSE
Requires-Dist: pandas
Requires-Dist: tf-explain
Requires-Dist: numpy
Requires-Dist: pillow
Requires-Dist: tqdm
Requires-Dist: cmapy
Requires-Dist: albumentations
Requires-Dist: matplotlib
Requires-Dist: seaborn
Requires-Dist: sklearn
Requires-Dist: pydicom
Provides-Extra: test
Requires-Dist: pytest ; extra == 'test'
